{"id":"chesapeake-country-scenic-byway","generatedAt":"2026-07-10T18:28:12.009Z","designation":"All-American Road","parkCode":null,"source":{"roadArticle":"List of Maryland Scenic Byways","revisionId":1353254799,"url":"https://en.wikipedia.org/wiki/Chesapeake_Country_Scenic_Byway"},"attribution":{"license":"CC BY-SA 4.0","licenseUrl":"https://creativecommons.org/licenses/by-sa/4.0/","articleUrl":"https://en.wikipedia.org/wiki/Chesapeake_Country_Scenic_Byway","text":"Route, junction, and history details adapted from the Wikipedia article \"List of Maryland Scenic Byways\", by Wikipedia contributors, licensed under CC BY-SA 4.0."},"sources":[{"name":"Wikipedia","src":"wikipedia","url":"https://en.wikipedia.org/wiki/Chesapeake_Country_Scenic_Byway","revisionId":1353254799,"retrievedAt":"2026-07-10T18:28:12.009Z"},{"name":"Federal Highway Administration — National Scenic Byways","src":"fhwa","url":"https://www.fhwa.dot.gov/byways","retrievedAt":"2026-07-10T18:28:12.009Z"}],"endpoints":null,"itinerary":[],"history":{"paragraphs":[],"sourceSection":null,"src":"wikipedia"},"highlights":[],"references":[{"n":1,"text":"\"Maryland Scenic Byways\" (PDF). Visit Maryland. Retrieved April 8, 2017.","url":"http://guides.milespartnership.com/md/Byways/16/"},{"n":2,"text":"\"Journey Through Hallowed Ground Byway\". National Scenic Byways Program. Archived from the original on November 10, 2013. Retrieved July 14, 2015.","url":"https://web.archive.org/web/20131110014708/http://www.fhwa.dot.gov/byways/byways/2343/maps"},{"n":3,"text":"\"Maryland Byways\" (PDF). Maryland State Highway Administration. Retrieved January 24, 2011.","url":"https://www.marylandroads.com/oed/MarylandScenicByways.pdf"},{"n":4,"text":"\"Baltimore's Historic Charles Street\". National Scenic Byways Program. Archived from the original on January 10, 2014. Retrieved July 14, 2015.","url":"https://web.archive.org/web/20140110112955/http://www.fhwa.dot.gov/byways/byways/2271/maps"},{"n":5,"text":"\"Religious Freedom Byway\". National Scenic Byways Program. Archived from the original on January 16, 2014. Retrieved July 14, 2015.","url":"https://web.archive.org/web/20140116001205/http://www.fhwa.dot.gov/byways/byways/40532/maps"},{"n":6,"text":"\"Harriet Tubman Underground Railroad Byway\". National Scenic Byways Program. Archived from the original on January 9, 2014. Retrieved July 14, 2015.","url":"https://web.archive.org/web/20140109151042/http://www.fhwa.dot.gov/byways/byways/2260/maps"},{"n":7,"text":"\"Harriet Tubman Underground Railroad Byway\". Delaware Department of Transportation. Archived from the original on November 17, 2011. Retrieved January 7, 2012.","url":"https://web.archive.org/web/20111117230128/https://www.deldot.gov/information/community_programs_and_services/byways/railroad.shtml#byways_page"}]}