{"id":"haines-highway","generatedAt":"2026-07-10T18:35:17.820Z","designation":"National Scenic Byway","parkCode":null,"source":{"roadArticle":"Haines Highway","revisionId":1339101678,"url":"https://en.wikipedia.org/wiki/Haines_Highway"},"attribution":{"license":"CC BY-SA 4.0","licenseUrl":"https://creativecommons.org/licenses/by-sa/4.0/","articleUrl":"https://en.wikipedia.org/wiki/Haines_Highway","text":"Route, junction, and history details adapted from the Wikipedia article \"Haines Highway\", by Wikipedia contributors, licensed under CC BY-SA 4.0."},"sources":[{"name":"Wikipedia","src":"wikipedia","url":"https://en.wikipedia.org/wiki/Haines_Highway","revisionId":1339101678,"retrievedAt":"2026-07-10T18:35:17.820Z"},{"name":"Federal Highway Administration — National Scenic Byways","src":"fhwa","url":"https://www.fhwa.dot.gov/byways","retrievedAt":"2026-07-10T18:35:17.820Z"},{"name":"OpenStreetMap contributors (ODbL)","src":"osm","url":"https://www.openstreetmap.org/copyright","retrievedAt":"2026-07-10T18:35:17.820Z"}],"endpoints":{"from":"Haines, AK","to":"Haines Junction, AK","via":["Dalton Cache–Pleasant Camp Border Crossing, AK"]},"itinerary":[{"seq":1,"place":"Haines","state":"AK","kind":"terminus","mileFromStart":0,"toNextMi":39.7,"note":"The drive begins here","control":["Haines Ferry Terminal"],"lat":59.22932,"lng":-135.44143,"src":"wikipedia"},{"seq":2,"place":"Dalton Cache–Pleasant Camp Border Crossing","state":"AK","kind":"town","mileFromStart":39.7,"toNextMi":108.2,"note":"Junction toward Canada–United States borderNorthern terminus of AK-7; southern terminus of Hwy 3","control":["Canada–United States borderNorthern terminus of AK-7; southern terminus of Hwy 3"],"lat":59.45047,"lng":-136.36193,"src":"wikipedia"},{"seq":3,"place":"Haines Junction","state":"AK","kind":"terminus","mileFromStart":147.9,"toNextMi":null,"note":"The drive ends here","control":["Anchorage","Fairbanks","Whitehorse"],"lat":60.75251,"lng":-137.51008,"src":"wikipedia"}],"history":{"paragraphs":["The route was originally a trail used by Chilkat Tlingit traders, which eventually became the Dalton Trail. It was used by some prospectors during the Klondike Gold Rush of 1898-1899; other mining kept the lower Dalton Trail active through the years following its establishment. The British Columbia provincial government converted its portion of the trail to a wagon road in 1909 when copper mining began at Copper Butte and Mt. Glave. In 1911, 30 tons of ore were shipped from the mines.","The highway was built by the U.S. Army in 1943 as an alternate route from the Pacific Ocean to the Alaska Highway, in case the White Pass and Yukon Route railway from Skagway should be blocked. The total cost of the construction was US$13 million.","In the first decades after the war, maintenance was spotty at best; the road was plagued with blizzards in winter and mudslides in summer, and for a time in the 1960s and 1970s, all vehicles traveling the highway were monitored on radio. Year-round access was not achieved until 1963.","Complaints over the condition of the road, primarily in Alaska, led to the U.S. Congress-funded Shakwak reconstruction project. This project, covering the Haines Highway and the portion of the Alaska Highway from Haines Junction to the U.S. border, began in 1976 and was mostly complete by the 1980s, but is still continuing, providing grade improvements, rerouting of dangerous sections, and paving. Responsibility for maintenance is currently shared between the Alaska and Yukon governments."],"sourceSection":"History","src":"wikipedia"},"highlights":[{"n":"Haines","d":"The drive begins here","q":"Haines","lat":59.23388889,"lng":-135.44694444,"src":"wikipedia"},{"n":"Haines Junction","d":"The drive ends here","q":"Haines Junction","lat":60.75361111,"lng":-137.51083333,"src":"wikipedia"}],"references":[{"n":1,"text":"\"Haines Highway in AK, BC, and YT\" (Map). Google Maps. Retrieved January 10, 2018.","url":"https://www.google.ca/maps/@59.9494158,-137.6522014,8z?hl=en"}],"routeLine":[[59.22932,-135.44143],[59.23022,-135.44336],[59.23063,-135.4443],[59.23162,-135.44645],[59.23215,-135.44771],[59.23274,-135.44899],[59.23314,-135.44991],[59.23356,-135.45116],[59.23386,-135.45233],[59.23418,-135.4545],[59.23436,-135.45618],[59.2348,-135.46001],[59.23524,-135.4639],[59.23538,-135.465],[59.23564,-135.46674],[59.2359,-135.46793],[59.23643,-135.46942],[59.23702,-135.4708],[59.23751,-135.47147],[59.23823,-135.47218],[59.23882,-135.47345],[59.23922,-135.47471],[59.23938,-135.47596],[59.23957,-135.47735],[59.23995,-135.47859],[59.24116,-135.48057],[59.24157,-135.48148],[59.24198,-135.4828],[59.24228,-135.48387],[59.24252,-135.48507],[59.24279,-135.48642],[59.24298,-135.4878],[59.24304,-135.489],[59.24281,-135.49221],[59.24274,-135.49365],[59.24285,-135.49715],[59.24306,-135.50317],[59.24325,-135.5099],[59.24339,-135.51114],[59.24376,-135.51238],[59.24415,-135.51327],[59.24453,-135.51449],[59.24475,-135.51739],[59.24487,-135.5187],[59.24517,-135.51998],[59.2468,-135.52413],[59.24728,-135.5251],[59.24782,-135.52619],[59.24829,-135.52724],[59.24876,-135.52844],[59.24897,-135.53],[59.24889,-135.53132],[59.24828,-135.5339],[59.24812,-135.53511],[59.24809,-135.53629],[59.24819,-135.53765],[59.24841,-135.53923],[59.24869,-135.54042],[59.24916,-135.54141],[59.24986,-135.54216],[59.25308,-135.54317],[59.25368,-135.54344],[59.2542,-135.54399],[59.25463,-135.5448],[59.25641,-135.54955],[59.25712,-135.55145],[59.25757,-135.55291],[59.26015,-135.56393],[59.26042,-135.56514],[59.26063,-135.56633],[59.26154,-135.57307],[59.26274,-135.57999],[59.26312,-135.58222],[59.26349,-135.58453],[59.26372,-135.58605],[59.2642,-135.58784],[59.26526,-135.5912],[59.26555,-135.5922],[59.26582,-135.59365],[59.26605,-135.60125],[59.26611,-135.6037],[59.26635,-135.61166],[59.2666,-135.6138],[59.26695,-135.61692],[59.2666,-135.62374],[59.26615,-135.63219],[59.2665,-135.63466],[59.26926,-135.64174],[59.27048,-135.64703],[59.27162,-135.64964],[59.27247,-135.65387],[59.27344,-135.65665],[59.2763,-135.6614],[59.27683,-135.66264],[59.27901,-135.66857],[59.27983,-135.67059],[59.28048,-135.67404],[59.28115,-135.6756],[59.2817,-135.67722],[59.28257,-135.68004],[59.28304,-135.68076],[59.28386,-135.68129],[59.28495,-135.68178],[59.28602,-135.68323],[59.28753,-135.68675],[59.29026,-135.69118],[59.29195,-135.69423],[59.2928,-135.69638],[59.29412,-135.69864],[59.29676,-135.7014],[59.29957,-135.70523],[59.30094,-135.70763],[59.30176,-135.70963],[59.30644,-135.71297],[59.3089,-135.71673],[59.30988,-135.71874],[59.31051,-135.71954],[59.31254,-135.72062],[59.31311,-135.72153],[59.31347,-135.72278],[59.31366,-135.72437],[59.31366,-135.72708],[59.31389,-135.7287],[59.31439,-135.72993],[59.31557,-135.73169],[59.31723,-135.73281],[59.31905,-135.73351],[59.31997,-135.73387],[59.32093,-135.73508],[59.32215,-135.73654],[59.32376,-135.73765],[59.3249,-135.73844],[59.32598,-135.73964],[59.32729,-135.74132],[59.32797,-135.74263],[59.32839,-135.7436],[59.32922,-135.74573],[59.32972,-135.74664],[59.33028,-135.74712],[59.33095,-135.74734],[59.33167,-135.74722],[59.33257,-135.74731],[59.33327,-135.7479],[59.3337,-135.74869],[59.33424,-135.7503],[59.33469,-135.75132],[59.33682,-135.7545],[59.33883,-135.75643],[59.33966,-135.75759],[59.34026,-135.75881],[59.34181,-135.76186],[59.34321,-135.76439],[59.34614,-135.76864],[59.34747,-135.77064],[59.34904,-135.77283],[59.34993,-135.77328],[59.35057,-135.77353],[59.3512,-135.77429],[59.35168,-135.77532],[59.35241,-135.77697],[59.35355,-135.77868],[59.35397,-135.78014],[59.35432,-135.78177],[59.35474,-135.78396],[59.3552,-135.78525],[59.35601,-135.78632],[59.35786,-135.78662],[59.3587,-135.78744],[59.35959,-135.78858],[59.36047,-135.78972],[59.36091,-135.79061],[59.36115,-135.79176],[59.36146,-135.79458],[59.36179,-135.79601],[59.36218,-135.79695],[59.36268,-135.79777],[59.36331,-135.79842],[59.36391,-135.79906],[59.36445,-135.79971],[59.36509,-135.80057],[59.36571,-135.802],[59.366,-135.80332],[59.36611,-135.80452],[59.36605,-135.80614],[59.36568,-135.81003],[59.3654,-135.81308],[59.36553,-135.81441],[59.36592,-135.81649],[59.36663,-135.81993],[59.36763,-135.82503],[59.36876,-135.82825],[59.36925,-135.82958],[59.36981,-135.83057],[59.37163,-135.83312],[59.37432,-135.83578],[59.37523,-135.83623],[59.37735,-135.83708],[59.37797,-135.83733],[59.37918,-135.83784],[59.37993,-135.8384],[59.38063,-135.83928],[59.38153,-135.84173],[59.38238,-135.84325],[59.38342,-135.84417],[59.38442,-135.84576],[59.38521,-135.84836],[59.38562,-135.84969],[59.38627,-135.85098],[59.38763,-135.85254],[59.38847,-135.85361],[59.38886,-135.85478],[59.38909,-135.85617],[59.38958,-135.85819],[59.3903,-135.86001],[59.39069,-135.86118],[59.39124,-135.8628],[59.39188,-135.8643],[59.39256,-135.86554],[59.3932,-135.86657],[59.39419,-135.86735],[59.39563,-135.86981],[59.39666,-135.87163],[59.39757,-135.87334],[59.39836,-135.87488],[59.39917,-135.87638],[59.39968,-135.87762],[59.40006,-135.87889],[59.40027,-135.88026],[59.40086,-135.88803],[59.40103,-135.89069],[59.40126,-135.89332],[59.40143,-135.89442],[59.40168,-135.89593],[59.40207,-135.8976],[59.40242,-135.89894],[59.40294,-135.90045],[59.40355,-135.90204],[59.40508,-135.90504],[59.40614,-135.90708],[59.40683,-135.90871],[59.40766,-135.91145],[59.40839,-135.91394],[59.40886,-135.9153],[59.40925,-135.91623],[59.41051,-135.91833],[59.41155,-135.92011],[59.41246,-135.92175],[59.41336,-135.92306],[59.41438,-135.92426],[59.41507,-135.925],[59.4156,-135.92608],[59.41597,-135.92775],[59.41595,-135.92955],[59.41547,-135.93143],[59.41479,-135.93364],[59.41444,-135.93492],[59.41377,-135.93714],[59.41324,-135.93898],[59.41248,-135.94174],[59.41169,-135.9467],[59.41107,-135.95044],[59.41072,-135.95258],[59.41029,-135.95522],[59.41005,-135.95739],[59.40995,-135.96024],[59.40983,-135.96635],[59.40981,-135.96853],[59.40992,-135.97104],[59.41015,-135.97327],[59.4104,-135.97507],[59.41061,-135.9766],[59.41082,-135.97808],[59.4111,-135.97974],[59.41151,-135.98173],[59.41185,-135.98319],[59.41214,-135.98432],[59.4128,-135.98664],[59.41327,-135.98855],[59.41358,-135.98989],[59.41372,-135.99111],[59.41373,-135.99251],[59.41352,-135.9942],[59.4133,-135.99546],[59.41312,-135.99741],[59.41317,-135.99855],[59.41341,-135.99972],[59.41433,-136.00221],[59.41481,-136.00328],[59.41556,-136.00505],[59.41629,-136.00673],[59.41699,-136.00846],[59.4178,-136.01005],[59.41831,-136.01091],[59.41933,-136.01159],[59.42011,-136.012],[59.42073,-136.01239],[59.42214,-136.01389],[59.42268,-136.01572],[59.42344,-136.01924],[59.42401,-136.02173],[59.42425,-136.02319],[59.42423,-136.02512],[59.42394,-136.02691],[59.42351,-136.0281],[59.42307,-136.029],[59.42257,-136.03032],[59.42227,-136.03168],[59.42216,-136.03355],[59.42226,-136.03475],[59.42238,-136.03631],[59.42271,-136.03953],[59.42279,-136.0407],[59.42278,-136.04223],[59.42268,-136.04358],[59.42244,-136.04579],[59.42232,-136.04721],[59.42229,-136.04918],[59.42244,-136.05229],[59.4225,-136.05441],[59.42249,-136.05631],[59.42244,-136.05755],[59.42235,-136.05908],[59.4221,-136.0626],[59.42194,-136.06472],[59.42163,-136.06669],[59.42062,-136.07095],[59.42028,-136.07266],[59.42011,-136.07383],[59.41994,-136.07573],[59.41988,-136.07721],[59.41991,-136.07858],[59.41999,-136.07986],[59.42016,-136.08159],[59.42059,-136.08604],[59.42084,-136.08894],[59.42148,-136.09605],[59.42166,-136.09765],[59.42218,-136.10083],[59.4226,-136.10272],[59.42294,-136.10408],[59.42336,-136.10577],[59.42382,-136.1075],[59.42418,-136.10902],[59.42485,-136.11157],[59.4253,-136.11332],[59.42592,-136.11572],[59.42641,-136.11682],[59.42687,-136.11807],[59.42779,-136.12066],[59.42804,-136.12183],[59.42808,-136.12376],[59.42789,-136.12769],[59.42785,-136.1299],[59.42792,-136.13129],[59.42814,-136.13274],[59.42863,-136.13582],[59.42915,-136.13934],[59.4295,-136.14264],[59.42957,-136.14387],[59.42965,-136.14697],[59.42979,-136.14857],[59.43015,-136.15043],[59.43055,-136.15258],[59.43081,-136.15462],[59.43093,-136.15631],[59.43095,-136.15795],[59.43095,-136.15941],[59.43094,-136.16783],[59.43093,-136.17677],[59.43096,-136.17796],[59.43104,-136.17924],[59.43117,-136.18061],[59.43137,-136.18207],[59.43156,-136.18346],[59.4318,-136.18512],[59.43223,-136.1881],[59.43244,-136.18962],[59.43286,-136.19252],[59.43302,-136.19363],[59.43325,-136.19522],[59.4338,-136.19904],[59.43401,-136.20093],[59.43409,-136.20212],[59.43412,-136.20353],[59.43409,-136.2051],[59.43402,-136.2063],[59.43328,-136.21313],[59.43291,-136.21652],[59.43271,-136.21853],[59.43262,-136.21978],[59.43257,-136.22115],[59.43259,-136.22315],[59.43265,-136.22444],[59.43274,-136.22559],[59.43288,-136.22684],[59.43476,-136.24131],[59.4362,-136.25206],[59.43829,-136.26886],[59.43914,-136.27846],[59.43933,-136.28094],[59.43934,-136.28333],[59.43915,-136.28514],[59.43745,-136.29226],[59.43696,-136.29452],[59.4369,-136.29651],[59.43699,-136.29891],[59.43694,-136.30125],[59.43665,-136.30322],[59.43601,-136.30788],[59.43575,-136.31125],[59.43571,-136.31373],[59.43603,-136.31606],[59.43653,-136.3174],[59.43743,-136.31871],[59.43801,-136.31914],[59.43869,-136.32001],[59.43933,-136.32165],[59.43984,-136.32412],[59.44013,-136.32555],[59.44035,-136.32717],[59.44063,-136.33075],[59.44076,-136.33351],[59.44117,-136.34036],[59.4414,-136.342],[59.4419,-136.34369],[59.44347,-136.34633],[59.44512,-136.34895],[59.44605,-136.35048],[59.44683,-136.35187],[59.44751,-136.35321],[59.44883,-136.35619],[59.44934,-136.35744],[59.44995,-136.35939],[59.45022,-136.36052],[59.45043,-136.36166],[59.45064,-136.36287],[59.45115,-136.36386],[59.45176,-136.36424],[59.45253,-136.3644],[59.45311,-136.36464],[59.45377,-136.36534],[59.45454,-136.36665],[59.45501,-136.36734],[59.4556,-136.36838],[59.45608,-136.36924],[59.45655,-136.37026],[59.45701,-136.37168],[59.45777,-136.3754],[59.45825,-136.37741],[59.45864,-136.37867],[59.46019,-136.38258],[59.46066,-136.3837],[59.46123,-136.38506],[59.46265,-136.3882],[59.46405,-136.39132],[59.46449,-136.39246],[59.46493,-136.39398],[59.46527,-136.39568],[59.46548,-136.39724],[59.46574,-136.39938],[59.46593,-136.40107],[59.46602,-136.40248],[59.46612,-136.40394],[59.46629,-136.40564],[59.46652,-136.40671],[59.46689,-136.40777],[59.4673,-136.40859],[59.46788,-136.40939],[59.46865,-136.40982],[59.46924,-136.40989],[59.46996,-136.40982],[59.47077,-136.40933],[59.47151,-136.40878],[59.47225,-136.40826],[59.47372,-136.40706],[59.47445,-136.40656],[59.47515,-136.40641],[59.47586,-136.40643],[59.47652,-136.40676],[59.47713,-136.40729],[59.47769,-136.40807],[59.47821,-136.40908],[59.48039,-136.41396],[59.48107,-136.4153],[59.48188,-136.41671],[59.48271,-136.41803],[59.48391,-136.42008],[59.48555,-136.42282],[59.48601,-136.42366],[59.48644,-136.42457],[59.48763,-136.42727],[59.48933,-136.43122],[59.4899,-136.43225],[59.49055,-136.43319],[59.49117,-136.43388],[59.49216,-136.43477],[59.49303,-136.43566],[59.49416,-136.43725],[59.49611,-136.4405],[59.49691,-136.4417],[59.49818,-136.44311],[59.49957,-136.44462],[59.50035,-136.44569],[59.50317,-136.45082],[59.50436,-136.45228],[59.50492,-136.45265],[59.50591,-136.45305],[59.50828,-136.45374],[59.51094,-136.45441],[59.51162,-136.45472],[59.51235,-136.45522],[59.51624,-136.45861],[59.51716,-136.45919],[59.51793,-136.45952],[59.51905,-136.45964],[59.52004,-136.45942],[59.5209,-136.459],[59.52269,-136.45762],[59.52391,-136.45691],[59.5252,-136.45643],[59.5296,-136.45535],[59.5307,-136.4554],[59.5319,-136.45553],[59.53303,-136.45586],[59.53434,-136.45651],[59.53818,-136.45867],[59.53959,-136.45919],[59.54509,-136.46082],[59.54638,-136.46151],[59.54738,-136.46228],[59.54821,-136.46308],[59.55125,-136.46701],[59.55203,-136.46784],[59.55268,-136.46832],[59.55335,-136.46869],[59.55421,-136.46895],[59.55493,-136.46901],[59.55562,-136.46893],[59.5646,-136.4671],[59.56669,-136.4668],[59.56744,-136.46675],[59.56912,-136.4668],[59.57013,-136.46663],[59.5709,-136.46651],[59.57591,-136.46513],[59.57965,-136.46456],[59.58081,-136.46462],[59.58167,-136.46489],[59.5823,-136.46523],[59.58448,-136.4668],[59.58529,-136.46724],[59.58592,-136.46747],[59.58678,-136.46754],[59.58775,-136.46741],[59.58871,-136.46683],[59.59042,-136.46527],[59.59134,-136.46419],[59.59546,-136.4588],[59.59661,-136.45722],[59.5978,-136.45599],[59.59855,-136.45543],[59.60081,-136.45442],[59.60214,-136.45384],[59.60337,-136.45331],[59.6045,-136.45293],[59.60853,-136.45266],[59.61083,-136.45255],[59.61203,-136.45226],[59.61384,-136.45142],[59.61493,-136.45084],[59.61715,-136.44964],[59.62066,-136.44744],[59.62149,-136.44732],[59.62258,-136.44741],[59.62347,-136.44761],[59.62431,-136.44799],[59.62501,-136.44847],[59.62568,-136.44912],[59.62923,-136.45337],[59.63005,-136.45419],[59.63266,-136.45607],[59.63367,-136.45701],[59.63474,-136.45824],[59.63889,-136.46405],[59.64488,-136.47243],[59.64571,-136.47372],[59.64622,-136.47463],[59.6477,-136.47783],[59.6483,-136.47889],[59.65272,-136.48536],[59.6533,-136.48634],[59.65378,-136.48733],[59.65415,-136.4883],[59.65455,-136.48954],[59.6551,-136.49183],[59.65644,-136.49964],[59.65733,-136.50731],[59.65762,-136.50906],[59.65805,-136.51113],[59.65927,-136.51577],[59.6599,-136.51864],[59.66498,-136.54365],[59.66576,-136.54699],[59.66661,-136.54993],[59.66737,-136.5523],[59.66888,-136.5563],[59.66929,-136.55723],[59.6719,-136.56279],[59.67324,-136.56513],[59.67493,-136.56768],[59.67656,-136.56968],[59.68891,-136.58281],[59.69005,-136.58389],[59.6943,-136.58693],[59.69541,-136.58803],[59.69963,-136.59304],[59.70021,-136.59386],[59.70081,-136.59478],[59.70132,-136.5958],[59.70237,-136.5981],[59.70502,-136.60391],[59.70566,-136.60501],[59.7065,-136.60617],[59.70731,-136.60696],[59.70831,-136.60764],[59.70922,-136.60796],[59.70995,-136.60807],[59.71088,-136.60801],[59.71305,-136.60742],[59.71994,-136.60555],[59.72103,-136.60512],[59.72327,-136.60366],[59.73373,-136.5963],[59.73473,-136.59548],[59.73592,-136.59423],[59.74115,-136.58807],[59.74208,-136.5873],[59.7432,-136.58674],[59.74397,-136.58657],[59.7447,-136.58656],[59.74554,-136.58671],[59.75542,-136.58972],[59.75672,-136.59036],[59.76126,-136.59302],[59.76604,-136.59507],[59.76711,-136.59535],[59.76867,-136.59554],[59.77069,-136.59537],[59.77984,-136.59436],[59.78075,-136.59413],[59.78358,-136.593],[59.78465,-136.59287],[59.7858,-136.59308],[59.78658,-136.59348],[59.78801,-136.59465],[59.79193,-136.59844],[59.79309,-136.59969],[59.79375,-136.60052],[59.79475,-136.60193],[59.79573,-136.60353],[59.79639,-136.60472],[59.79741,-136.60687],[59.79794,-136.60814],[59.80021,-136.61453],[59.8008,-136.61594],[59.80145,-136.61726],[59.8022,-136.61839],[59.80277,-136.61913],[59.80393,-136.62045],[59.80755,-136.62456],[59.80838,-136.62536],[59.81045,-136.62702],[59.82282,-136.63629],[59.82404,-136.63705],[59.8252,-136.63755],[59.82638,-136.63783],[59.82775,-136.63791],[59.82914,-136.6377],[59.83277,-136.63677],[59.83366,-136.63674],[59.83447,-136.63689],[59.83545,-136.6373],[59.83625,-136.63792],[59.83698,-136.63863],[59.83752,-136.63935],[59.83811,-136.64031],[59.83856,-136.64111],[59.83899,-136.64204],[59.83944,-136.6434],[59.84127,-136.64943],[59.842,-136.65156],[59.84276,-136.6533],[59.84355,-136.65489],[59.8445,-136.65649],[59.84537,-136.65775],[59.8463,-136.65884],[59.8528,-136.66529],[59.85367,-136.66638],[59.85439,-136.66742],[59.85543,-136.66919],[59.86555,-136.69071],[59.86639,-136.69226],[59.86724,-136.6935],[59.87879,-136.70603],[59.87938,-136.7067],[59.88019,-136.70777],[59.88088,-136.70889],[59.88153,-136.71002],[59.8821,-136.71112],[59.88263,-136.71224],[59.88353,-136.71449],[59.88411,-136.7163],[59.88459,-136.71783],[59.88606,-136.72361],[59.88743,-136.72946],[59.88795,-136.73149],[59.8886,-136.73355],[59.88897,-136.73447],[59.89134,-136.74072],[59.89208,-136.74239],[59.89284,-136.74384],[59.90208,-136.76051],[59.90263,-136.76158],[59.90335,-136.76319],[59.90393,-136.76467],[59.9095,-136.78116],[59.91073,-136.78403],[59.91166,-136.78553],[59.91654,-136.7912],[59.92082,-136.79614],[59.92188,-136.79714],[59.92247,-136.79755],[59.92339,-136.79791],[59.92413,-136.79806],[59.94019,-136.79957],[59.94242,-136.79992],[59.94362,-136.80032],[59.94462,-136.80082],[59.94565,-136.80148],[59.94687,-136.80243],[59.95209,-136.80702],[59.95366,-136.80818],[59.96017,-136.81255],[59.96544,-136.81592],[59.96683,-136.81661],[59.96806,-136.81699],[59.97368,-136.81807],[59.97445,-136.81826],[59.97518,-136.81858],[59.976,-136.81917],[59.97672,-136.81991],[59.97741,-136.8208],[59.97804,-136.82183],[59.98669,-136.84051],[59.98729,-136.84156],[59.98813,-136.84272],[59.98897,-136.84352],[59.99001,-136.84407],[59.9907,-136.84426],[59.99188,-136.84444],[59.99258,-136.84453],[59.9952,-136.84495],[59.99634,-136.8452],[59.99778,-136.84589],[59.99954,-136.84719],[60.00628,-136.85231],[60.01339,-136.85709],[60.0144,-136.8579],[60.01535,-136.85886],[60.01618,-136.86001],[60.01693,-136.86129],[60.01806,-136.86329],[60.01883,-136.86457],[60.01967,-136.86566],[60.02372,-136.86946],[60.02521,-136.87081],[60.03727,-136.88173],[60.03817,-136.88246],[60.03906,-136.88294],[60.03992,-136.88323],[60.04377,-136.88321],[60.04465,-136.88326],[60.04742,-136.88409],[60.04943,-136.88479],[60.05041,-136.88542],[60.05179,-136.88699],[60.05629,-136.89302],[60.0572,-136.89406],[60.05814,-136.89476],[60.05913,-136.89519],[60.06215,-136.8954],[60.06314,-136.89564],[60.0641,-136.89614],[60.06503,-136.89691],[60.07489,-136.90896],[60.07577,-136.90991],[60.07669,-136.91063],[60.07764,-136.91117],[60.07861,-136.9115],[60.07961,-136.91159],[60.0806,-136.91149],[60.08257,-136.91103],[60.08357,-136.91098],[60.08456,-136.91123],[60.08552,-136.91179],[60.08643,-136.91265],[60.08852,-136.91536],[60.08945,-136.91612],[60.09042,-136.91661],[60.09141,-136.91679],[60.09241,-136.91663],[60.09337,-136.91618],[60.09535,-136.91466],[60.09615,-136.91403],[60.0971,-136.91345],[60.0981,-136.91318],[60.09909,-136.91326],[60.10008,-136.91366],[60.10103,-136.91431],[60.1019,-136.91529],[60.10312,-136.917],[60.10399,-136.91806],[60.10755,-136.92174],[60.10886,-136.92315],[60.10969,-136.92429],[60.11035,-136.92561],[60.11078,-136.92673],[60.11133,-136.92851],[60.11221,-136.93138],[60.11253,-136.93254],[60.11278,-136.93381],[60.11291,-136.93521],[60.11291,-136.9369],[60.11263,-136.93967],[60.11254,-136.94152],[60.11263,-136.94334],[60.11314,-136.94589],[60.11445,-136.95095],[60.11488,-136.9526],[60.11535,-136.95419],[60.11623,-136.95628],[60.11698,-136.9575],[60.11803,-136.95887],[60.11922,-136.95982],[60.12003,-136.96019],[60.12235,-136.96078],[60.12335,-136.96107],[60.12408,-136.96139],[60.12479,-136.96179],[60.12585,-136.96255],[60.1276,-136.96421],[60.13448,-136.97101],[60.1364,-136.97287],[60.13761,-136.9739],[60.13845,-136.97453],[60.1401,-136.97552],[60.1409,-136.97591],[60.14166,-136.97623],[60.14239,-136.97649],[60.14307,-136.97668],[60.14423,-136.97691],[60.15267,-136.97819],[60.15413,-136.97873],[60.15506,-136.97934],[60.15596,-136.98017],[60.15934,-136.98441],[60.16048,-136.98564],[60.16114,-136.98623],[60.16209,-136.98687],[60.16355,-136.98751],[60.16505,-136.98778],[60.16655,-136.98762],[60.16905,-136.9868],[60.17005,-136.98652],[60.17156,-136.98652],[60.17255,-136.98679],[60.17353,-136.98729],[60.18555,-136.99414],[60.1884,-136.99572],[60.1899,-136.99603],[60.19091,-136.99588],[60.19188,-136.99543],[60.19329,-136.99429],[60.19415,-136.99324],[60.19581,-136.9911],[60.19696,-136.98924],[60.19764,-136.98781],[60.19826,-136.98622],[60.19976,-136.98095],[60.20032,-136.97927],[60.20097,-136.97774],[60.20206,-136.97571],[60.20289,-136.97457],[60.20549,-136.97155],[60.20763,-136.96897],[60.2085,-136.96798],[60.20943,-136.96713],[60.2104,-136.96654],[60.21141,-136.96622],[60.21638,-136.96563],[60.21725,-136.96553],[60.22031,-136.9652],[60.22181,-136.96475],[60.22278,-136.96423],[60.22372,-136.96355],[60.22509,-136.96226],[60.22635,-136.96066],[60.22722,-136.95957],[60.22859,-136.95828],[60.22955,-136.95768],[60.23104,-136.95721],[60.23203,-136.95718],[60.23503,-136.95734],[60.23604,-136.95735],[60.23704,-136.9573],[60.23854,-136.95712],[60.23953,-136.95692],[60.24152,-136.95645],[60.243,-136.95632],[60.2445,-136.95652],[60.24549,-136.95685],[60.24793,-136.95808],[60.24993,-136.95914],[60.25082,-136.95971],[60.25176,-136.96042],[60.25312,-136.96169],[60.25443,-136.96318],[60.25691,-136.96656],[60.25777,-136.96757],[60.2601,-136.96947],[60.26103,-136.97025],[60.26195,-136.97108],[60.26328,-136.97251],[60.26456,-136.97413],[60.26578,-136.97588],[60.26693,-136.97781],[60.26803,-136.97985],[60.27167,-136.9868],[60.27242,-136.98815],[60.27323,-136.98937],[60.27408,-136.99045],[60.27498,-136.99139],[60.2759,-136.99217],[60.27686,-136.99281],[60.27784,-136.99329],[60.28191,-136.99494],[60.2842,-136.99588],[60.28514,-136.99644],[60.28603,-136.99735],[60.28681,-136.99857],[60.28744,-136.99996],[60.28776,-137.00093],[60.29184,-137.0194],[60.29304,-137.02499],[60.29355,-137.02672],[60.29418,-137.02828],[60.29492,-137.02961],[60.29577,-137.0307],[60.29947,-137.03355],[60.30837,-137.04006],[60.30982,-137.04086],[60.31081,-137.04124],[60.3118,-137.04154],[60.31725,-137.04289],[60.32133,-137.04395],[60.32237,-137.04422],[60.3316,-137.0466],[60.33408,-137.04712],[60.33508,-137.0472],[60.33609,-137.04721],[60.33759,-137.04708],[60.34803,-137.04525],[60.34903,-137.0451],[60.35002,-137.04513],[60.351,-137.0455],[60.35194,-137.04622],[60.353,-137.04747],[60.35368,-137.04816],[60.35461,-137.04884],[60.35558,-137.04919],[60.3617,-137.05033],[60.36251,-137.05048],[60.364,-137.05079],[60.36495,-137.05128],[60.36584,-137.05219],[60.36722,-137.05403],[60.36874,-137.05606],[60.36959,-137.05709],[60.37037,-137.05769],[60.37101,-137.05799],[60.37202,-137.05811],[60.37301,-137.05783],[60.37395,-137.05716],[60.3748,-137.05611],[60.37629,-137.05343],[60.37711,-137.05241],[60.37784,-137.05173],[60.37908,-137.05126],[60.38096,-137.05121],[60.3818,-137.05106],[60.38244,-137.0508],[60.38303,-137.05051],[60.38437,-137.04967],[60.38583,-137.04917],[60.39377,-137.04765],[60.39476,-137.04755],[60.39575,-137.04756],[60.39675,-137.04768],[60.39807,-137.04798],[60.40372,-137.04924],[60.4052,-137.04953],[60.40619,-137.04958],[60.40718,-137.04953],[60.40866,-137.04924],[60.40966,-137.04892],[60.41258,-137.04754],[60.41404,-137.04698],[60.41552,-137.04671],[60.4165,-137.04668],[60.41748,-137.04676],[60.41843,-137.04695],[60.41939,-137.04725],[60.42034,-137.04765],[60.42176,-137.04845],[60.42315,-137.04957],[60.42407,-137.05045],[60.42496,-137.05139],[60.42589,-137.05216],[60.42688,-137.05255],[60.4279,-137.05247],[60.43685,-137.05],[60.43784,-137.04981],[60.43879,-137.04992],[60.43972,-137.05043],[60.44329,-137.0535],[60.44422,-137.05424],[60.44562,-137.05524],[60.44705,-137.05606],[60.4485,-137.05673],[60.45505,-137.05915],[60.46004,-137.06099],[60.4615,-137.06143],[60.46248,-137.06164],[60.46345,-137.06177],[60.46443,-137.06182],[60.46592,-137.06176],[60.46691,-137.06164],[60.47176,-137.06064],[60.47567,-137.05989],[60.47665,-137.05975],[60.47763,-137.05971],[60.47861,-137.05971],[60.48008,-137.05984],[60.48203,-137.06024],[60.48346,-137.06069],[60.49116,-137.06359],[60.4926,-137.06419],[60.49355,-137.06467],[60.49496,-137.06556],[60.49588,-137.06622],[60.49723,-137.06739],[60.49812,-137.06823],[60.49899,-137.06916],[60.5,-137.07039],[60.50187,-137.07286],[60.50353,-137.07497],[60.50642,-137.07873],[60.50726,-137.07974],[60.50812,-137.08062],[60.50902,-137.08139],[60.50993,-137.08203],[60.51647,-137.08622],[60.51738,-137.08692],[60.5187,-137.0882],[60.52036,-137.0903],[60.52805,-137.10044],[60.53526,-137.10994],[60.53824,-137.11382],[60.53991,-137.11586],[60.54417,-137.12052],[60.54594,-137.12253],[60.54676,-137.12364],[60.54753,-137.12484],[60.5486,-137.12686],[60.54957,-137.12908],[60.55822,-137.14956],[60.56883,-137.17473],[60.57402,-137.18706],[60.5778,-137.19602],[60.57936,-137.19973],[60.58031,-137.20204],[60.58095,-137.20362],[60.58194,-137.20591],[60.58323,-137.20896],[60.5837,-137.21014],[60.58419,-137.21135],[60.58638,-137.2167],[60.58737,-137.21926],[60.59073,-137.22788],[60.59123,-137.22911],[60.59187,-137.23081],[60.5925,-137.23241],[60.59294,-137.23353],[60.59351,-137.23485],[60.59463,-137.23679],[60.59589,-137.23837],[60.59753,-137.2402],[60.60629,-137.25],[60.608,-137.25191],[60.60923,-137.25357],[60.61,-137.25481],[60.61111,-137.25679],[60.61187,-137.25805],[60.61269,-137.25918],[60.61355,-137.26019],[60.61444,-137.26106],[60.62074,-137.26664],[60.62298,-137.26868],[60.62382,-137.26969],[60.6246,-137.27091],[60.6253,-137.27231],[60.62591,-137.27389],[60.62643,-137.27561],[60.62684,-137.27745],[60.62714,-137.27939],[60.62802,-137.28755],[60.62824,-137.28944],[60.62841,-137.29094],[60.62865,-137.29286],[60.629,-137.29471],[60.62945,-137.29647],[60.63002,-137.29811],[60.63067,-137.29961],[60.63141,-137.30094],[60.63315,-137.30377],[60.64488,-137.32284],[60.64605,-137.32465],[60.64687,-137.32579],[60.64812,-137.32738],[60.66679,-137.34785],[60.6691,-137.35053],[60.67109,-137.35284],[60.67536,-137.35787],[60.67744,-137.36023],[60.68525,-137.36909],[60.68698,-137.37101],[60.68783,-137.37205],[60.68904,-137.37377],[60.6898,-137.37505],[60.69052,-137.37644],[60.70047,-137.39744],[60.70186,-137.40033],[60.70296,-137.40237],[60.70414,-137.40424],[60.71645,-137.42247],[60.71727,-137.42363],[60.71814,-137.42461],[60.71905,-137.42542],[60.7205,-137.42617],[60.72149,-137.42639],[60.72247,-137.42635],[60.72543,-137.42549],[60.72642,-137.42542],[60.7274,-137.4256],[60.72836,-137.42603],[60.72927,-137.4267],[60.73054,-137.42813],[60.73132,-137.42937],[60.73199,-137.43074],[60.73255,-137.43229],[60.7338,-137.43634],[60.73432,-137.43783],[60.73517,-137.4398],[60.7363,-137.44191],[60.73711,-137.44349],[60.73774,-137.44506],[60.73827,-137.44681],[60.73867,-137.44842],[60.73906,-137.45022],[60.73933,-137.45224],[60.73994,-137.45872],[60.74116,-137.47239],[60.74191,-137.48041],[60.74337,-137.49744],[60.74357,-137.4992],[60.74391,-137.50088],[60.74436,-137.5023],[60.7448,-137.50334],[60.7454,-137.50438],[60.74602,-137.50519],[60.74687,-137.50592],[60.74756,-137.50643],[60.74862,-137.50721],[60.74996,-137.50818],[60.75071,-137.50874],[60.75131,-137.5092],[60.75224,-137.50989],[60.75251,-137.51008]],"routeSource":"OpenStreetMap","routeMiles":148,"pois":[{"name":"Three Guardsman Lake","type":"lake","lat":59.61089,"lng":-136.44942,"mile":52.7},{"name":"Chilkat Pass","type":"pass","lat":59.66929,"lng":-136.55723,"mile":58.8},{"name":"Kusawak Lake","type":"lake","lat":59.6876,"lng":-136.58437,"mile":60.5},{"name":"Twin Lakes","type":"lake","lat":59.888,"lng":-136.73767,"mile":76.7},{"name":"Tatshenshini River","type":"lake","lat":59.90778,"lng":-136.79318,"mile":79},{"name":"Takhanne River","type":"lake","lat":60.11406,"lng":-136.92205,"mile":94.1},{"name":"Million Dollar Falls","type":"overlook","lat":60.10853,"lng":-136.94674,"mile":94.8},{"name":"Million Dollar Falls","type":"waterfall","lat":60.10868,"lng":-136.94699,"mile":94.8},{"name":"Scenic overlook","type":"overlook","lat":60.12554,"lng":-136.96329,"mile":95.9},{"name":"Pringle Lake","type":"lake","lat":60.12997,"lng":-136.97925,"mile":96.6},{"name":"Stella Lake","type":"lake","lat":60.16741,"lng":-136.99663,"mile":98.9},{"name":"Klukshu River","type":"lake","lat":60.27069,"lng":-136.98955,"mile":107},{"name":"Kathleen River","type":"lake","lat":60.58941,"lng":-137.23118,"mile":132.4},{"name":"Dezedeash River Trailhead","type":"trailhead","lat":60.74837,"lng":-137.50883,"mile":147.6},{"name":"Dezadeash River","type":"lake","lat":60.74647,"lng":-137.51899,"mile":147.6}],"gallery":[{"url":"https://upload.wikimedia.org/wikipedia/commons/thumb/f/f5/5_Mile_Creek.jpg/1280px-5_Mile_Creek.jpg","full":"https://upload.wikimedia.org/wikipedia/commons/f/f5/5_Mile_Creek.jpg","cap":"5 Mile Creek","desc":"Photo by Micah Bochart, Haines Highway Mile 46 in British Columbia","credit":"Giskard mb at English Wikipedia · Public domain","pageUrl":"https://commons.wikimedia.org/wiki/File:5_Mile_Creek.jpg"},{"url":"https://upload.wikimedia.org/wikipedia/commons/b/b0/Cathedral_Peaks.jpg","full":"https://upload.wikimedia.org/wikipedia/commons/b/b0/Cathedral_Peaks.jpg","cap":"Cathedral Peaks","desc":"Photo by Micah Bochart, Mile 8 of Haines Highway - Mt. Emmerich and the Chilkat River","credit":"Giskard mb at English Wikipedia · Public domain","pageUrl":"https://commons.wikimedia.org/wiki/File:Cathedral_Peaks.jpg"},{"url":"https://upload.wikimedia.org/wikipedia/commons/thumb/a/a9/Chilkat_Pass.jpg/1280px-Chilkat_Pass.jpg","full":"https://upload.wikimedia.org/wikipedia/commons/a/a9/Chilkat_Pass.jpg","cap":"Chilkat Pass","desc":"Photo by Micah Bochart, Haines Highway, Chilkat Pass","credit":"Giskard mb at English Wikipedia · Public domain","pageUrl":"https://commons.wikimedia.org/wiki/File:Chilkat_Pass.jpg"},{"url":"https://upload.wikimedia.org/wikipedia/commons/2/22/Haines_Highway.jpg","full":"https://upload.wikimedia.org/wikipedia/commons/2/22/Haines_Highway.jpg","cap":"Haines Highway","desc":"Haines Highway","credit":"Andrei from New York City/Juneau, U.S.A. · CC BY 2.0","pageUrl":"https://commons.wikimedia.org/wiki/File:Haines_Highway.jpg"},{"url":"https://upload.wikimedia.org/wikipedia/commons/7/75/Haines_Highway_%281%29.jpg","full":"https://upload.wikimedia.org/wikipedia/commons/7/75/Haines_Highway_%281%29.jpg","cap":"(1)","desc":"Haines Highway","credit":"Andrei from New York City/Juneau, U.S.A. · CC BY 2.0","pageUrl":"https://commons.wikimedia.org/wiki/File:Haines_Highway_(1).jpg"},{"url":"https://upload.wikimedia.org/wikipedia/commons/thumb/0/04/Haines_Highway_110805.jpg/1280px-Haines_Highway_110805.jpg","full":"https://upload.wikimedia.org/wikipedia/commons/0/04/Haines_Highway_110805.jpg","cap":"110805","desc":"P1000481.jpg","credit":"Bo Mertz · CC BY-SA 2.0","pageUrl":"https://commons.wikimedia.org/wiki/File:Haines_Highway_110805.jpg"},{"url":"https://upload.wikimedia.org/wikipedia/commons/thumb/f/f8/Haines_Highway_-_Valley_of_the_Eagles_-_33-Mile_Roadhouse_Restaurant_-_NARA_-_7719070.jpg/1280px-Haines_Highway_-_Valley_of_the_Eagles_-_33-Mile_Roadhouse_Restaurant_-_NARA_-_7719070.jpg","full":"https://upload.wikimedia.org/wikipedia/commons/f/f8/Haines_Highway_-_Valley_of_the_Eagles_-_33-Mile_Roadhouse_Restaurant_-_NARA_-_7719070.jpg","cap":"Valley of the Eagles 33 Mile Roadhouse Restaurant","desc":"The 33-Mile Roadhouse along the Haines Highway is a small haven known for its specialty hamburgers. Fuel services are also available. Location: Location: Alaska Status: Public domain. Lori Stepansky","credit":"Public domain","pageUrl":"https://commons.wikimedia.org/wiki/File:Haines_Highway_-_Valley_of_the_Eagles_-_33-Mile_Roadhouse_Restaurant_-_NARA_-_7719070.jpg"},{"url":"https://upload.wikimedia.org/wikipedia/commons/1/11/Haines_Highway_-_Valley_of_the_Eagles_-_Anway_House_-_NARA_-_7719072.jpg","full":"https://upload.wikimedia.org/wikipedia/commons/1/11/Haines_Highway_-_Valley_of_the_Eagles_-_Anway_House_-_NARA_-_7719072.jpg","cap":"Valley of the Eagles Anway House","desc":"In this vintage photo, founder and owner Charles Anway stands by his home, today known as the Anway Homestead House. Location: Location: Alaska Status: Public domain. Courtesy of Sheldon Museum","credit":"Public domain","pageUrl":"https://commons.wikimedia.org/wiki/File:Haines_Highway_-_Valley_of_the_Eagles_-_Anway_House_-_NARA_-_7719072.jpg"},{"url":"https://upload.wikimedia.org/wikipedia/commons/thumb/5/56/Haines_Highway_-_Valley_of_the_Eagles_-_Approaching_Porcupine_Crossing_in_Autumn_-_NARA_-_7719086.jpg/1280px-Haines_Highway_-_Valley_of_the_Eagles_-_Approaching_Porcupine_Crossing_in_Autumn_-_NARA_-_7719086.jpg","full":"https://upload.wikimedia.org/wikipedia/commons/5/56/Haines_Highway_-_Valley_of_the_Eagles_-_Approaching_Porcupine_Crossing_in_Autumn_-_NARA_-_7719086.jpg","cap":"Valley of the Eagles Approaching Porcupine Crossing in Autumn","desc":"Haines Highway bei Mosquito Lake; Abzweig zur Porcupine Bridge über den Klehini River nach Covenant Life CDP","credit":"Public domain","pageUrl":"https://commons.wikimedia.org/wiki/File:Haines_Highway_-_Valley_of_the_Eagles_-_Approaching_Porcupine_Crossing_in_Autumn_-_NARA_-_7719086.jpg"},{"url":"https://upload.wikimedia.org/wikipedia/commons/thumb/7/77/Haines_Highway_-_Valley_of_the_Eagles_-_Approaching_the_Kluktoo_Slide_Area_-_NARA_-_7719082.jpg/1280px-Haines_Highway_-_Valley_of_the_Eagles_-_Approaching_the_Kluktoo_Slide_Area_-_NARA_-_7719082.jpg","full":"https://upload.wikimedia.org/wikipedia/commons/7/77/Haines_Highway_-_Valley_of_the_Eagles_-_Approaching_the_Kluktoo_Slide_Area_-_NARA_-_7719082.jpg","cap":"Valley of the Eagles Approaching the Kluktoo Slide Area","desc":"The northbound Haines Highway approaches the area of an old slide which devastated the Tlingit village of Kluktoo. Location: Location: Kluktoo, Alaska Status: Public domain. Lori Stepansky","credit":"Public domain","pageUrl":"https://commons.wikimedia.org/wiki/File:Haines_Highway_-_Valley_of_the_Eagles_-_Approaching_the_Kluktoo_Slide_Area_-_NARA_-_7719082.jpg"},{"url":"https://upload.wikimedia.org/wikipedia/commons/thumb/f/fc/Haines_Highway_-_Valley_of_the_Eagles_-_Council_Grounds_-_NARA_-_7719079.jpg/1280px-Haines_Highway_-_Valley_of_the_Eagles_-_Council_Grounds_-_NARA_-_7719079.jpg","full":"https://upload.wikimedia.org/wikipedia/commons/f/fc/Haines_Highway_-_Valley_of_the_Eagles_-_Council_Grounds_-_NARA_-_7719079.jpg","cap":"Valley of the Eagles Council Grounds","desc":"The Council Grounds informational pullout has information kiosks where visitors can learn more about the Alaska Chilkat Bald Eagle Preserve. Location: Location: Alaska Chilkat Bald Eagle Preserve, Alaska Status: Public domain. Lori Stepansky","credit":"Public domain","pageUrl":"https://commons.wikimedia.org/wiki/File:Haines_Highway_-_Valley_of_the_Eagles_-_Council_Grounds_-_NARA_-_7719079.jpg"},{"url":"https://upload.wikimedia.org/wikipedia/commons/thumb/d/d6/Haines_Highway_-_Valley_of_the_Eagles_-_Haines_Highway--Valley_of_the_Eagles_-_NARA_-_7719078.jpg/1280px-Haines_Highway_-_Valley_of_the_Eagles_-_Haines_Highway--Valley_of_the_Eagles_-_NARA_-_7719078.jpg","full":"https://upload.wikimedia.org/wikipedia/commons/d/d6/Haines_Highway_-_Valley_of_the_Eagles_-_Haines_Highway--Valley_of_the_Eagles_-_NARA_-_7719078.jpg","cap":"Valley of the Eagles Valley of the Eagles","desc":"At Mile Point 32, the driver sees the road heading directly north with the mountains of Alaska and Canada on the horizon and catches his or her breath knowing the only connection between them and this untouched, natural setting is the Haines Highway itself. Location: Location: Alaska (59.412° N 135.945° W) Status: Public domain. Lori Stepansky","credit":"Public domain","pageUrl":"https://commons.wikimedia.org/wiki/File:Haines_Highway_-_Valley_of_the_Eagles_-_Haines_Highway--Valley_of_the_Eagles_-_NARA_-_7719078.jpg"},{"url":"https://upload.wikimedia.org/wikipedia/commons/thumb/e/e1/Haines_Highway_-_Valley_of_the_Eagles_-_Interpretive_Signage_at_North_Council_Grounds_Pull-out_-_NARA_-_7719085.jpg/1280px-Haines_Highway_-_Valley_of_the_Eagles_-_Interpretive_Signage_at_North_Council_Grounds_Pull-out_-_NARA_-_7719085.jpg","full":"https://upload.wikimedia.org/wikipedia/commons/e/e1/Haines_Highway_-_Valley_of_the_Eagles_-_Interpretive_Signage_at_North_Council_Grounds_Pull-out_-_NARA_-_7719085.jpg","cap":"Valley of the Eagles Interpretive Signage at North Council Grounds Pul","desc":"Interpretive panels about eagles stand under shelters at North Council Grounds, where visitors can see views of the river valley. Location: Location: North Council Grounds, Alaska Status: Public domain. Lori Stepansky","credit":"Public domain","pageUrl":"https://commons.wikimedia.org/wiki/File:Haines_Highway_-_Valley_of_the_Eagles_-_Interpretive_Signage_at_North_Council_Grounds_Pull-out_-_NARA_-_7719085.jpg"},{"url":"https://upload.wikimedia.org/wikipedia/commons/thumb/d/d4/Haines_Highway_-_Valley_of_the_Eagles_-_Klehini_River_Scenic_Viewing_Area_-_NARA_-_7719084.jpg/1280px-Haines_Highway_-_Valley_of_the_Eagles_-_Klehini_River_Scenic_Viewing_Area_-_NARA_-_7719084.jpg","full":"https://upload.wikimedia.org/wikipedia/commons/d/d4/Haines_Highway_-_Valley_of_the_Eagles_-_Klehini_River_Scenic_Viewing_Area_-_NARA_-_7719084.jpg","cap":"Valley of the Eagles Klehini River Scenic Viewing Area","desc":"An interpretive panel at the Klehini River Scenic Viewing Area describes the history of expanse of the Chilkat River Valley. The area also provides scopes to look for wildlife along the banks of the river and eagles in the trees. Location: Location: Haines Burough, Alaska Status: Public domain. Lori Stepansky","credit":"Public domain","pageUrl":"https://commons.wikimedia.org/wiki/File:Haines_Highway_-_Valley_of_the_Eagles_-_Klehini_River_Scenic_Viewing_Area_-_NARA_-_7719084.jpg"},{"url":"https://upload.wikimedia.org/wikipedia/commons/thumb/a/a0/Haines_Highway_-_Valley_of_the_Eagles_-_Low_Hanging_Clouds_at_the_Kluktoo_Slide_Area_-_NARA_-_7719081.jpg/1280px-Haines_Highway_-_Valley_of_the_Eagles_-_Low_Hanging_Clouds_at_the_Kluktoo_Slide_Area_-_NARA_-_7719081.jpg","full":"https://upload.wikimedia.org/wikipedia/commons/a/a0/Haines_Highway_-_Valley_of_the_Eagles_-_Low_Hanging_Clouds_at_the_Kluktoo_Slide_Area_-_NARA_-_7719081.jpg","cap":"Valley of the Eagles Low Hanging Clouds at the Kluktoo Slide Area","desc":"Clouds hang low over a russet-colored mountainside as a vehicle passes by one of the green mile markers on the Haines Highway at the Kluktoo Slide area. Location: Location: Kluktoo Slide Area, Alaska Status: Public domain. Lori Stepansky","credit":"Public domain","pageUrl":"https://commons.wikimedia.org/wiki/File:Haines_Highway_-_Valley_of_the_Eagles_-_Low_Hanging_Clouds_at_the_Kluktoo_Slide_Area_-_NARA_-_7719081.jpg"},{"url":"https://upload.wikimedia.org/wikipedia/commons/thumb/2/2e/Haines_Highway_-_Valley_of_the_Eagles_-_Signage_for_Entering_the_Eagle_Preserve_-_NARA_-_7719075.jpg/1280px-Haines_Highway_-_Valley_of_the_Eagles_-_Signage_for_Entering_the_Eagle_Preserve_-_NARA_-_7719075.jpg","full":"https://upload.wikimedia.org/wikipedia/commons/2/2e/Haines_Highway_-_Valley_of_the_Eagles_-_Signage_for_Entering_the_Eagle_Preserve_-_NARA_-_7719075.jpg","cap":"Valley of the Eagles Signage for Entering the Eagle Preserve","desc":"Driving up the Haines Highway, you know you are entering the Alaska Chilkat Bald Eagle Preserve from the sign on the right. Location: Location: Near Haines, Alaska Status: Public domain. Lori Stepansky","credit":"Public domain","pageUrl":"https://commons.wikimedia.org/wiki/File:Haines_Highway_-_Valley_of_the_Eagles_-_Signage_for_Entering_the_Eagle_Preserve_-_NARA_-_7719075.jpg"},{"url":"https://upload.wikimedia.org/wikipedia/commons/thumb/a/a9/Haines_Highway_-_Valley_of_the_Eagles_-_Totem_in_the_Klukwan_Village_Long_House_-_NARA_-_7719083.jpg/1280px-Haines_Highway_-_Valley_of_the_Eagles_-_Totem_in_the_Klukwan_Village_Long_House_-_NARA_-_7719083.jpg","full":"https://upload.wikimedia.org/wikipedia/commons/a/a9/Haines_Highway_-_Valley_of_the_Eagles_-_Totem_in_the_Klukwan_Village_Long_House_-_NARA_-_7719083.jpg","cap":"Valley of the Eagles Totem in the Klukwan Village Long House","desc":"A totem within the legendary walls of the Tlingit's Long House smiles at visitors, encouraging them on their journey. Location: Location: Haines, Alaska Status: Public domain. Lori Stepansky","credit":"Public domain","pageUrl":"https://commons.wikimedia.org/wiki/File:Haines_Highway_-_Valley_of_the_Eagles_-_Totem_in_the_Klukwan_Village_Long_House_-_NARA_-_7719083.jpg"},{"url":"https://upload.wikimedia.org/wikipedia/commons/thumb/6/63/Haines_Highway_-_Valley_of_the_Eagles_-_Visitors_Viewing_Fish_Wheel_Activities_-_NARA_-_7719076.jpg/1280px-Haines_Highway_-_Valley_of_the_Eagles_-_Visitors_Viewing_Fish_Wheel_Activities_-_NARA_-_7719076.jpg","full":"https://upload.wikimedia.org/wikipedia/commons/6/63/Haines_Highway_-_Valley_of_the_Eagles_-_Visitors_Viewing_Fish_Wheel_Activities_-_NARA_-_7719076.jpg","cap":"Valley of the Eagles Visitors Viewing Fish Wheel Activities","desc":"Two Chinese visitors photograph the fish wheel in action while another fish wheel can be seen in place down river in the background. Location: Location: Alaska Status: Public domain. Lori Stepansky","credit":"Public domain","pageUrl":"https://commons.wikimedia.org/wiki/File:Haines_Highway_-_Valley_of_the_Eagles_-_Visitors_Viewing_Fish_Wheel_Activities_-_NARA_-_7719076.jpg"}]}