{"id":"mountains-to-sound-greenway","generatedAt":"2026-07-10T18:35:17.820Z","designation":"National Scenic Byway","parkCode":null,"source":{"roadArticle":"Mountains to Sound Greenway","revisionId":1322608630,"url":"https://en.wikipedia.org/wiki/Mountains_to_Sound_Greenway"},"attribution":{"license":"CC BY-SA 4.0","licenseUrl":"https://creativecommons.org/licenses/by-sa/4.0/","articleUrl":"https://en.wikipedia.org/wiki/Mountains_to_Sound_Greenway","text":"Route, junction, and history details adapted from the Wikipedia article \"Mountains to Sound Greenway\", by Wikipedia contributors, licensed under CC BY-SA 4.0."},"sources":[{"name":"Wikipedia","src":"wikipedia","url":"https://en.wikipedia.org/wiki/Mountains_to_Sound_Greenway","revisionId":1322608630,"retrievedAt":"2026-07-10T18:35:17.820Z"},{"name":"Federal Highway Administration — National Scenic Byways","src":"fhwa","url":"https://www.fhwa.dot.gov/byways","retrievedAt":"2026-07-10T18:35:17.820Z"},{"name":"OpenStreetMap contributors (ODbL)","src":"osm","url":"https://www.openstreetmap.org/copyright","retrievedAt":"2026-07-10T18:35:17.820Z"}],"endpoints":null,"itinerary":[{"place":"Mountains to Sound Greenway (start)","mileFromStart":0,"kind":"terminus","lat":47.85691,"lng":-121.95988,"seq":1,"src":"openstreetmap","control":[],"note":"The drive begins here","toNextMi":11.8},{"place":"Olney Falls","mileFromStart":11.8,"kind":"crossing","lat":47.87842,"lng":-121.71787,"seq":2,"src":"openstreetmap","control":[],"note":"","toNextMi":6.3},{"place":"View of railroad bridge","mileFromStart":18.1,"kind":"overlook","lat":47.82109,"lng":-121.62307,"seq":3,"src":"openstreetmap","control":[],"note":"","toNextMi":0.1},{"place":"View of Baring Mountain","mileFromStart":18.2,"kind":"overlook","lat":47.81971,"lng":-121.62053,"seq":4,"src":"openstreetmap","control":[],"note":"","toNextMi":0.8},{"place":"Boulder Drop","mileFromStart":19,"kind":"crossing","lat":47.81662,"lng":-121.60028,"seq":5,"src":"openstreetmap","control":[],"note":"","toNextMi":2.7},{"place":"Sunset Falls","mileFromStart":21.7,"kind":"crossing","lat":47.80425,"lng":-121.5493,"seq":6,"src":"openstreetmap","control":[],"note":"","toNextMi":0.3},{"place":"Canyon Falls Viewpoint","mileFromStart":22,"kind":"overlook","lat":47.81272,"lng":-121.54537,"seq":7,"src":"openstreetmap","control":[],"note":"","toNextMi":0},{"place":"Bridal Veil Falls Viewpoint","mileFromStart":22,"kind":"overlook","lat":47.81241,"lng":-121.55091,"seq":8,"src":"openstreetmap","control":[],"note":"","toNextMi":0.7},{"place":"Canyon Falls","mileFromStart":22.7,"kind":"crossing","lat":47.8038,"lng":-121.53494,"seq":9,"src":"openstreetmap","control":[],"note":"","toNextMi":1.3},{"place":"Eagle Falls","mileFromStart":24,"kind":"crossing","lat":47.79591,"lng":-121.51444,"seq":10,"src":"openstreetmap","control":[],"note":"","toNextMi":16.2},{"place":"Alpine Falls","mileFromStart":40.2,"kind":"crossing","lat":47.71682,"lng":-121.22625,"seq":11,"src":"openstreetmap","control":[],"note":"","toNextMi":1.5},{"place":"Scenic overlook","mileFromStart":41.7,"kind":"overlook","lat":47.71491,"lng":-121.19435,"seq":12,"src":"openstreetmap","control":[],"note":"","toNextMi":0},{"place":"Deception Falls","mileFromStart":41.7,"kind":"crossing","lat":47.71458,"lng":-121.19449,"seq":13,"src":"openstreetmap","control":[],"note":"","toNextMi":0},{"place":"Monkey Cage Falls","mileFromStart":41.7,"kind":"crossing","lat":47.71693,"lng":-121.19495,"seq":14,"src":"openstreetmap","control":[],"note":"","toNextMi":0.5},{"place":"Twin Tunnels landmark","mileFromStart":42.2,"kind":"overlook","lat":47.71841,"lng":-121.1824,"seq":15,"src":"openstreetmap","control":[],"note":"","toNextMi":16.6},{"place":"Mountains to Sound Greenway (end)","mileFromStart":58.8,"kind":"terminus","lat":47.78146,"lng":-121.04425,"seq":16,"src":"openstreetmap","control":[],"note":"The drive ends here"}],"history":{"paragraphs":[],"sourceSection":null,"src":"wikipedia"},"highlights":[],"references":[{"n":1,"text":"Gutman, David (March 12, 2019). \"Federal lands bill creates National Heritage Area from Seattle to Ellensburg\". The Seattle Times. Retrieved March 13, 2019.","url":"https://www.seattletimes.com/seattle-news/politics/federal-lands-bill-creates-national-heritage-area-from-seattle-to-ellensburg/"},{"n":2,"text":"Metzger, Katie (April 10, 2019). \"Mountains to Sound Greenway designated as a National Heritage Area\". Enumclaw Courier-Herald. Retrieved April 11, 2019.","url":"https://www.courierherald.com/northwest/mountains-to-sound-greenway-designated-as-a-national-heritage-area/"},{"n":3,"text":"Paulson, Michael (June 10, 1998). \"Stretch of Rainier road joins scenic elite\". Seattle Post-Intelligencer. p. B1.","url":""},{"n":4,"text":"Carlton Harrell, Debera (June 7, 2003). \"Greenway trailblazers on mountain high\". Seattle Post-Intelligencer. p. A1. Retrieved October 6, 2021.","url":"https://www.seattlepi.com/news/article/Greenway-trailblazers-on-mountain-high-1116595.php"},{"n":5,"text":"Fefer, Mark D. (April 27, 2000). \"Big green money machine\". Seattle Weekly. Archived from the original on October 30, 2002. Retrieved September 28, 2021.","url":"https://web.archive.org/web/20021030223202/http://www.seattleweekly.com/features/0017/features-fefer.shtml"}],"routeLine":[[47.85691,-121.95988],[47.85673,-121.95893],[47.85651,-121.95734],[47.85641,-121.95624],[47.85635,-121.95509],[47.85636,-121.9535],[47.85641,-121.95228],[47.85663,-121.94994],[47.85673,-121.94854],[47.85682,-121.94742],[47.85685,-121.94606],[47.8568,-121.94505],[47.85674,-121.94385],[47.85666,-121.94237],[47.85625,-121.93458],[47.85615,-121.9328],[47.85591,-121.92788],[47.85586,-121.92685],[47.85549,-121.91998],[47.85524,-121.91544],[47.85506,-121.91209],[47.85482,-121.90765],[47.85477,-121.90597],[47.8548,-121.90486],[47.85492,-121.9036],[47.85507,-121.90258],[47.85541,-121.90084],[47.85554,-121.89969],[47.8555,-121.89565],[47.85547,-121.89437],[47.85537,-121.8911],[47.85533,-121.88893],[47.85522,-121.88759],[47.85472,-121.88459],[47.85336,-121.87668],[47.85237,-121.87078],[47.85175,-121.86716],[47.85124,-121.86419],[47.85103,-121.86269],[47.851,-121.8615],[47.85105,-121.86063],[47.85116,-121.85971],[47.85131,-121.85882],[47.85228,-121.85279],[47.85261,-121.85111],[47.8529,-121.8499],[47.85527,-121.84117],[47.85644,-121.83683],[47.85698,-121.83481],[47.85796,-121.83117],[47.85822,-121.83018],[47.85848,-121.82918],[47.85899,-121.82731],[47.85921,-121.82648],[47.85947,-121.82552],[47.85984,-121.82413],[47.86021,-121.82273],[47.86057,-121.82139],[47.86105,-121.81957],[47.86139,-121.81836],[47.86169,-121.81708],[47.86178,-121.81607],[47.8618,-121.81499],[47.86182,-121.81405],[47.86186,-121.81215],[47.86187,-121.81115],[47.86189,-121.81017],[47.86198,-121.80911],[47.86209,-121.80812],[47.86232,-121.80707],[47.86253,-121.80618],[47.86292,-121.80455],[47.86319,-121.80351],[47.86357,-121.80219],[47.86401,-121.80074],[47.86433,-121.79968],[47.86505,-121.79744],[47.86544,-121.796],[47.8656,-121.79515],[47.86602,-121.79213],[47.86624,-121.79057],[47.86634,-121.78972],[47.86661,-121.78771],[47.86674,-121.78666],[47.86693,-121.78515],[47.86711,-121.7838],[47.86726,-121.78276],[47.86738,-121.78186],[47.86751,-121.78096],[47.86761,-121.77996],[47.86772,-121.77895],[47.86787,-121.77812],[47.86767,-121.77998],[47.86785,-121.77783],[47.86801,-121.77675],[47.86818,-121.77562],[47.86813,-121.7767],[47.86826,-121.77531],[47.86836,-121.77446],[47.86866,-121.77214],[47.86893,-121.76997],[47.86914,-121.76841],[47.86928,-121.76739],[47.86945,-121.76605],[47.86964,-121.7642],[47.86968,-121.7632],[47.86965,-121.76209],[47.86956,-121.76114],[47.86934,-121.75969],[47.86908,-121.75862],[47.86866,-121.75684],[47.86844,-121.75588],[47.86777,-121.75303],[47.86748,-121.75178],[47.86729,-121.75067],[47.86719,-121.74947],[47.86717,-121.74824],[47.86717,-121.74708],[47.86718,-121.74591],[47.86719,-121.74442],[47.86718,-121.74249],[47.86718,-121.74137],[47.86718,-121.74029],[47.86718,-121.73915],[47.86718,-121.73807],[47.86719,-121.73694],[47.86716,-121.7349],[47.86709,-121.73385],[47.86683,-121.7323],[47.86659,-121.73107],[47.86638,-121.72967],[47.86633,-121.72812],[47.86631,-121.72473],[47.86629,-121.72333],[47.86624,-121.7218],[47.86601,-121.72051],[47.8657,-121.71945],[47.86514,-121.71827],[47.86386,-121.71579],[47.86318,-121.71448],[47.86227,-121.71272],[47.86172,-121.71166],[47.86108,-121.71042],[47.86059,-121.70944],[47.86008,-121.70848],[47.85956,-121.70747],[47.85921,-121.70669],[47.85836,-121.70485],[47.85797,-121.70388],[47.85765,-121.70309],[47.85707,-121.70177],[47.85663,-121.70087],[47.85627,-121.70019],[47.85571,-121.69907],[47.85531,-121.6983],[47.8546,-121.69694],[47.85405,-121.69587],[47.8535,-121.69482],[47.85296,-121.69376],[47.85241,-121.69267],[47.85151,-121.69093],[47.85089,-121.68972],[47.85051,-121.68904],[47.85007,-121.68818],[47.84958,-121.68714],[47.84902,-121.68602],[47.84859,-121.68517],[47.84804,-121.68412],[47.84764,-121.68336],[47.84705,-121.68224],[47.8466,-121.68138],[47.8459,-121.68004],[47.84511,-121.67856],[47.84462,-121.67754],[47.84415,-121.67649],[47.84379,-121.67557],[47.84336,-121.67439],[47.84299,-121.67334],[47.84243,-121.6718],[47.84164,-121.66948],[47.84085,-121.66717],[47.84048,-121.66609],[47.83996,-121.66455],[47.83946,-121.66323],[47.83913,-121.66231],[47.83843,-121.66016],[47.83768,-121.65799],[47.83724,-121.65673],[47.8369,-121.65575],[47.83642,-121.65435],[47.83565,-121.65214],[47.83459,-121.64902],[47.83421,-121.64727],[47.83409,-121.64635],[47.83403,-121.64546],[47.83401,-121.64422],[47.83405,-121.64332],[47.83414,-121.64212],[47.83426,-121.64078],[47.83449,-121.63799],[47.83495,-121.63254],[47.83505,-121.63132],[47.8356,-121.62459],[47.83568,-121.62344],[47.83562,-121.62226],[47.83547,-121.62141],[47.83498,-121.61997],[47.83432,-121.61891],[47.83357,-121.61816],[47.83299,-121.61779],[47.83218,-121.61745],[47.83152,-121.61733],[47.8309,-121.61745],[47.83013,-121.61796],[47.82921,-121.61886],[47.82846,-121.61941],[47.8278,-121.61965],[47.82705,-121.61966],[47.82639,-121.61941],[47.82576,-121.61899],[47.82526,-121.61843],[47.82449,-121.61749],[47.82286,-121.61551],[47.8215,-121.61392],[47.82058,-121.61286],[47.81992,-121.61206],[47.81915,-121.61059],[47.81758,-121.6067],[47.81725,-121.60579],[47.81687,-121.60438],[47.81644,-121.60241],[47.81616,-121.60153],[47.81528,-121.59957],[47.81473,-121.59826],[47.81452,-121.59729],[47.81462,-121.59606],[47.81497,-121.59497],[47.8155,-121.59387],[47.81574,-121.59303],[47.81583,-121.59197],[47.81574,-121.59083],[47.81549,-121.58998],[47.81506,-121.58908],[47.81343,-121.58591],[47.81304,-121.58491],[47.81279,-121.58375],[47.8126,-121.58254],[47.81238,-121.58109],[47.81227,-121.58],[47.81237,-121.57914],[47.81302,-121.57724],[47.81348,-121.57593],[47.81375,-121.57492],[47.81384,-121.57404],[47.8138,-121.57286],[47.81362,-121.57167],[47.81338,-121.57067],[47.8129,-121.56987],[47.8123,-121.56933],[47.81175,-121.56898],[47.81124,-121.56855],[47.81075,-121.56781],[47.81037,-121.56655],[47.81013,-121.56531],[47.80971,-121.5639],[47.80929,-121.56305],[47.80887,-121.56221],[47.80856,-121.56136],[47.80812,-121.55974],[47.80787,-121.5588],[47.80761,-121.5578],[47.80747,-121.5564],[47.80754,-121.5549],[47.80755,-121.55396],[47.8072,-121.55218],[47.80712,-121.55079],[47.80719,-121.54985],[47.80749,-121.54875],[47.80809,-121.54757],[47.80936,-121.54596],[47.80985,-121.5451],[47.81016,-121.54393],[47.81024,-121.54306],[47.81019,-121.54107],[47.81006,-121.53975],[47.80984,-121.53884],[47.80708,-121.53274],[47.80635,-121.53116],[47.80551,-121.52958],[47.80461,-121.52792],[47.80422,-121.52696],[47.80403,-121.52595],[47.80403,-121.52502],[47.80418,-121.52409],[47.80447,-121.52306],[47.80464,-121.52165],[47.80463,-121.51983],[47.80449,-121.51863],[47.80419,-121.51771],[47.80355,-121.51673],[47.80289,-121.51624],[47.8016,-121.5159],[47.8001,-121.51564],[47.79949,-121.51552],[47.79869,-121.51523],[47.7974,-121.51456],[47.79592,-121.5138],[47.79498,-121.51333],[47.79342,-121.51281],[47.79272,-121.5123],[47.79143,-121.51004],[47.79094,-121.50916],[47.78933,-121.50634],[47.78815,-121.50421],[47.7869,-121.50199],[47.78652,-121.50125],[47.78615,-121.50048],[47.78573,-121.49965],[47.7851,-121.49873],[47.78461,-121.49821],[47.78385,-121.4977],[47.78249,-121.497],[47.7819,-121.49669],[47.78132,-121.49639],[47.78038,-121.49563],[47.77992,-121.49508],[47.77784,-121.49244],[47.77726,-121.49169],[47.77434,-121.48798],[47.77284,-121.48606],[47.77075,-121.48341],[47.76896,-121.48114],[47.76796,-121.47986],[47.76618,-121.47757],[47.76202,-121.47229],[47.75956,-121.46918],[47.75854,-121.4679],[47.75417,-121.46233],[47.75357,-121.46129],[47.75321,-121.46035],[47.75294,-121.45947],[47.75264,-121.45789],[47.75241,-121.45697],[47.75197,-121.45567],[47.75097,-121.45406],[47.74983,-121.45271],[47.74701,-121.44896],[47.74656,-121.44838],[47.7461,-121.44754],[47.7458,-121.44652],[47.74564,-121.44568],[47.7454,-121.44452],[47.74505,-121.44322],[47.74467,-121.44229],[47.74417,-121.44137],[47.74353,-121.44053],[47.7425,-121.4396],[47.74183,-121.43897],[47.74126,-121.43806],[47.74087,-121.43717],[47.73955,-121.4341],[47.73598,-121.42568],[47.73558,-121.4248],[47.73484,-121.42314],[47.73411,-121.42145],[47.73369,-121.42042],[47.73336,-121.41956],[47.73303,-121.41866],[47.73221,-121.41639],[47.73171,-121.41495],[47.73144,-121.41413],[47.73125,-121.4133],[47.73108,-121.41203],[47.73102,-121.41114],[47.73091,-121.40947],[47.73081,-121.4085],[47.73059,-121.40753],[47.73028,-121.40666],[47.72942,-121.40517],[47.72902,-121.40447],[47.72861,-121.40335],[47.72819,-121.40167],[47.72793,-121.40058],[47.72756,-121.39906],[47.7272,-121.39793],[47.72688,-121.3972],[47.72629,-121.39625],[47.72521,-121.39504],[47.72427,-121.39413],[47.72188,-121.39204],[47.72116,-121.39128],[47.7207,-121.3907],[47.71991,-121.38922],[47.71926,-121.38719],[47.71808,-121.38352],[47.71722,-121.38122],[47.71621,-121.37922],[47.7153,-121.37814],[47.71461,-121.3775],[47.71355,-121.37632],[47.71267,-121.37507],[47.712,-121.3739],[47.71155,-121.37282],[47.71098,-121.37147],[47.71051,-121.36999],[47.71024,-121.36866],[47.71021,-121.36734],[47.71028,-121.36638],[47.71131,-121.36189],[47.71158,-121.36086],[47.71179,-121.36004],[47.71197,-121.35881],[47.71195,-121.35783],[47.71188,-121.35649],[47.71186,-121.35559],[47.71185,-121.35452],[47.71218,-121.3526],[47.71275,-121.35111],[47.71377,-121.34847],[47.71415,-121.34725],[47.71442,-121.34604],[47.7145,-121.3449],[47.71416,-121.34202],[47.71399,-121.34075],[47.71385,-121.33981],[47.71344,-121.33688],[47.7132,-121.33517],[47.71303,-121.33393],[47.71283,-121.3325],[47.71268,-121.33135],[47.71256,-121.3305],[47.71237,-121.32917],[47.71222,-121.32807],[47.71209,-121.32707],[47.71196,-121.32576],[47.71197,-121.3248],[47.71204,-121.32303],[47.71208,-121.32205],[47.71219,-121.31931],[47.71226,-121.3176],[47.71229,-121.31662],[47.71226,-121.31565],[47.71216,-121.31439],[47.71202,-121.31311],[47.71193,-121.31219],[47.71175,-121.3105],[47.71163,-121.30943],[47.71149,-121.30799],[47.71139,-121.30712],[47.71127,-121.30582],[47.71124,-121.30494],[47.71128,-121.30376],[47.71146,-121.30192],[47.71163,-121.30033],[47.71176,-121.29914],[47.71192,-121.29764],[47.71201,-121.29675],[47.71212,-121.29576],[47.71228,-121.2942],[47.71248,-121.29224],[47.7126,-121.2913],[47.71281,-121.29023],[47.71304,-121.28937],[47.71327,-121.28855],[47.71364,-121.28756],[47.7143,-121.28626],[47.71496,-121.2851],[47.7159,-121.28346],[47.71626,-121.28277],[47.71663,-121.28193],[47.71699,-121.28064],[47.71719,-121.27939],[47.71725,-121.27839],[47.7172,-121.27718],[47.7171,-121.27607],[47.71685,-121.27498],[47.71651,-121.27398],[47.71612,-121.27323],[47.71558,-121.27225],[47.71524,-121.27152],[47.71483,-121.27033],[47.71469,-121.26942],[47.71465,-121.26852],[47.71483,-121.26595],[47.71504,-121.26343],[47.71528,-121.26059],[47.7154,-121.25927],[47.71554,-121.25775],[47.71572,-121.25589],[47.71588,-121.25409],[47.71601,-121.25266],[47.71626,-121.24944],[47.71648,-121.24652],[47.71657,-121.24526],[47.71672,-121.2434],[47.71681,-121.2425],[47.71696,-121.24166],[47.71726,-121.24057],[47.7176,-121.23956],[47.71789,-121.23851],[47.71804,-121.23765],[47.71812,-121.23654],[47.71814,-121.23442],[47.71816,-121.23299],[47.71815,-121.23147],[47.71809,-121.23038],[47.71798,-121.22942],[47.71783,-121.22824],[47.71771,-121.22721],[47.71762,-121.22564],[47.71757,-121.2241],[47.71752,-121.22268],[47.71745,-121.22141],[47.71738,-121.22032],[47.71708,-121.21497],[47.71687,-121.21348],[47.71644,-121.2116],[47.71622,-121.21051],[47.71612,-121.20938],[47.71612,-121.20819],[47.71612,-121.20681],[47.71598,-121.20575],[47.71553,-121.20358],[47.71522,-121.20208],[47.71504,-121.20104],[47.7149,-121.19965],[47.71486,-121.19874],[47.71488,-121.1978],[47.71493,-121.19673],[47.71498,-121.19582],[47.71505,-121.19469],[47.71525,-121.19141],[47.71537,-121.18958],[47.71553,-121.18834],[47.7157,-121.18724],[47.71582,-121.18603],[47.71583,-121.18513],[47.71577,-121.18426],[47.71547,-121.18079],[47.71535,-121.17901],[47.71523,-121.17757],[47.71507,-121.17648],[47.71465,-121.17497],[47.71397,-121.17257],[47.71351,-121.1709],[47.71288,-121.16871],[47.71231,-121.16676],[47.712,-121.16571],[47.71155,-121.16417],[47.71127,-121.16319],[47.71099,-121.16219],[47.71082,-121.16118],[47.71075,-121.16022],[47.71077,-121.15935],[47.71087,-121.15844],[47.71111,-121.15708],[47.71146,-121.15523],[47.71163,-121.15436],[47.71179,-121.15348],[47.71202,-121.15224],[47.71221,-121.15119],[47.71238,-121.15032],[47.71265,-121.14888],[47.71288,-121.14764],[47.71351,-121.14447],[47.71419,-121.14095],[47.71437,-121.13996],[47.71462,-121.13891],[47.71484,-121.13811],[47.7153,-121.13665],[47.71558,-121.1358],[47.71616,-121.13403],[47.71646,-121.1331],[47.71669,-121.13217],[47.71679,-121.13114],[47.7167,-121.12789],[47.71666,-121.12673],[47.71663,-121.12567],[47.71673,-121.12456],[47.71695,-121.12372],[47.71739,-121.12301],[47.71801,-121.12264],[47.71863,-121.12264],[47.71921,-121.12304],[47.71962,-121.12372],[47.71983,-121.12457],[47.71989,-121.12547],[47.71991,-121.12452],[47.71968,-121.1236],[47.71923,-121.12288],[47.71868,-121.12249],[47.718,-121.12246],[47.7174,-121.12279],[47.71692,-121.12343],[47.71664,-121.12435],[47.71663,-121.12567],[47.71989,-121.12547],[47.71986,-121.12885],[47.71994,-121.12978],[47.72017,-121.13121],[47.72028,-121.13208],[47.72036,-121.13332],[47.72037,-121.1345],[47.72052,-121.13556],[47.72084,-121.13634],[47.72144,-121.13709],[47.72208,-121.13753],[47.72285,-121.13784],[47.724,-121.13793],[47.72504,-121.13786],[47.72766,-121.13716],[47.7287,-121.13686],[47.72932,-121.13663],[47.73006,-121.13618],[47.7309,-121.13554],[47.73161,-121.13499],[47.73224,-121.1344],[47.73392,-121.13251],[47.73448,-121.13187],[47.73615,-121.12982],[47.73678,-121.12906],[47.73727,-121.12854],[47.73828,-121.1275],[47.73884,-121.12695],[47.73938,-121.12654],[47.74025,-121.12602],[47.74118,-121.1254],[47.74194,-121.12483],[47.74256,-121.12432],[47.74363,-121.12344],[47.74462,-121.12262],[47.74522,-121.12212],[47.74584,-121.1216],[47.7464,-121.12079],[47.74672,-121.11998],[47.74703,-121.11885],[47.74717,-121.11748],[47.74724,-121.11637],[47.74727,-121.1151],[47.74734,-121.11303],[47.74742,-121.1112],[47.74749,-121.1096],[47.74754,-121.1079],[47.74753,-121.10638],[47.74756,-121.10539],[47.74784,-121.10345],[47.74798,-121.10214],[47.748,-121.10101],[47.74794,-121.10001],[47.7478,-121.09902],[47.74758,-121.09805],[47.7473,-121.09717],[47.74683,-121.09605],[47.74627,-121.09499],[47.74581,-121.09411],[47.7454,-121.09332],[47.74511,-121.09247],[47.745,-121.09153],[47.7451,-121.09046],[47.74536,-121.08965],[47.74576,-121.08901],[47.7466,-121.08809],[47.74706,-121.08736],[47.74741,-121.08659],[47.74782,-121.08534],[47.7482,-121.08453],[47.74985,-121.08198],[47.75038,-121.0812],[47.75105,-121.08021],[47.75167,-121.07949],[47.75242,-121.07882],[47.75354,-121.0779],[47.75509,-121.07664],[47.75583,-121.07615],[47.75658,-121.07579],[47.75749,-121.07555],[47.7584,-121.07536],[47.75901,-121.07526],[47.75974,-121.07528],[47.76046,-121.07543],[47.76205,-121.07621],[47.76281,-121.0766],[47.7634,-121.07687],[47.76398,-121.07711],[47.76485,-121.07739],[47.76577,-121.0776],[47.76694,-121.07774],[47.76772,-121.07777],[47.76854,-121.07771],[47.76929,-121.07746],[47.77001,-121.07702],[47.77069,-121.07637],[47.77128,-121.07569],[47.77208,-121.07474],[47.7727,-121.07393],[47.77336,-121.07297],[47.77406,-121.07182],[47.77444,-121.07117],[47.77482,-121.07051],[47.77556,-121.06931],[47.77603,-121.0686],[47.77653,-121.06789],[47.77747,-121.06665],[47.77839,-121.06513],[47.77889,-121.06423],[47.77931,-121.06343],[47.77964,-121.06269],[47.78013,-121.06139],[47.78056,-121.05999],[47.7811,-121.05762],[47.78149,-121.05581],[47.78166,-121.05468],[47.78168,-121.05347],[47.78149,-121.05219],[47.78108,-121.05044],[47.78089,-121.04921],[47.78089,-121.048],[47.78146,-121.04425],[47.78167,-121.0433],[47.78196,-121.04238],[47.78243,-121.04151],[47.7829,-121.04088],[47.78334,-121.04017],[47.78367,-121.03942],[47.78399,-121.03844],[47.78429,-121.03748],[47.78453,-121.03646],[47.78465,-121.03543],[47.78461,-121.03405],[47.78442,-121.03225],[47.78422,-121.03076],[47.78397,-121.02971],[47.7836,-121.02872],[47.78283,-121.02727],[47.78231,-121.0266],[47.78169,-121.026],[47.78085,-121.02531],[47.77903,-121.02368],[47.77793,-121.02274],[47.77721,-121.0219],[47.77686,-121.02121],[47.7757,-121.01804],[47.77536,-121.01702],[47.77454,-121.0145],[47.77414,-121.01279],[47.77361,-121.01039],[47.7733,-121.00864],[47.77302,-121.00643],[47.7729,-121.00545],[47.77279,-121.00455],[47.77257,-121.00338],[47.77225,-121.00243],[47.77184,-121.00169],[47.77139,-121.00106],[47.77173,-121.00182],[47.7723,-121.00313],[47.77259,-121.00457],[47.77271,-121.00563],[47.77278,-121.00732],[47.77268,-121.01169],[47.77266,-121.01284],[47.77297,-121.01454],[47.77327,-121.01542],[47.77403,-121.01695],[47.7755,-121.01996],[47.7764,-121.02187],[47.7772,-121.02304],[47.7777,-121.02355],[47.7799,-121.02537],[47.78152,-121.02663],[47.78205,-121.02711],[47.78261,-121.02774],[47.78311,-121.02848],[47.7836,-121.02947],[47.78387,-121.0304],[47.78409,-121.03161],[47.78421,-121.03265],[47.78433,-121.03367],[47.78436,-121.03479],[47.78424,-121.03576],[47.78407,-121.03658],[47.78303,-121.0393],[47.78215,-121.04133],[47.78173,-121.04252],[47.78153,-121.04355],[47.78146,-121.04425]],"routeSource":"OpenStreetMap","routeMiles":59,"pois":[{"name":"Susie's Trail","type":"trailhead","lat":47.86208,"lng":-121.82042,"mile":6.7},{"name":"Olney Falls","type":"waterfall","lat":47.87842,"lng":-121.71787,"mile":11.8},{"name":"Gold Bar Nature Trails","type":"campground","lat":47.84949,"lng":-121.648,"mile":15.5},{"name":"Little Haystack","type":"peak","lat":47.82215,"lng":-121.62581,"mile":18,"ele":437},{"name":"View of railroad bridge","type":"overlook","lat":47.82109,"lng":-121.62307,"mile":18.1},{"name":"View of Baring Mountain","type":"overlook","lat":47.81971,"lng":-121.62053,"mile":18.2},{"name":"Boulder Drop","type":"waterfall","lat":47.81662,"lng":-121.60028,"mile":19},{"name":"Lake Serene Trailhead","type":"trailhead","lat":47.80911,"lng":-121.57402,"mile":20.8},{"name":"Sunset Falls","type":"waterfall","lat":47.80425,"lng":-121.5493,"mile":21.7},{"name":"South Fork Skykomish River","type":"lake","lat":47.80435,"lng":-121.55027,"mile":21.7},{"name":"Canyon Falls Viewpoint","type":"overlook","lat":47.81272,"lng":-121.54537,"mile":22},{"name":"Bridal Veil Falls Viewpoint","type":"overlook","lat":47.81241,"lng":-121.55091,"mile":22},{"name":"Canyon Falls","type":"waterfall","lat":47.8038,"lng":-121.53494,"mile":22.7},{"name":"Heybrook Lookout Trailhead","type":"trailhead","lat":47.80835,"lng":-121.53506,"mile":22.7},{"name":"Heybrook Mountain","type":"peak","lat":47.81177,"lng":-121.52261,"mile":23.2,"ele":555},{"name":"Eagle Falls","type":"waterfall","lat":47.79591,"lng":-121.51444,"mile":24},{"name":"Skykomish Ballpark","type":"campground","lat":47.71195,"lng":-121.3474,"mile":34.3},{"name":"Cass Pond","type":"lake","lat":47.71353,"lng":-121.32364,"mile":35.5},{"name":"Profitts Pond","type":"lake","lat":47.71122,"lng":-121.26886,"mile":38.2,"ele":375},{"name":"Alpine Falls","type":"waterfall","lat":47.71682,"lng":-121.22625,"mile":40.2},{"name":"Scenic overlook","type":"overlook","lat":47.71491,"lng":-121.19435,"mile":41.7},{"name":"Deception Falls","type":"waterfall","lat":47.71458,"lng":-121.19449,"mile":41.7},{"name":"Monkey Cage Falls","type":"waterfall","lat":47.71693,"lng":-121.19495,"mile":41.7},{"name":"Deception Creek Trailhead","type":"trailhead","lat":47.71211,"lng":-121.19371,"mile":41.7},{"name":"Twin Tunnels landmark","type":"overlook","lat":47.71841,"lng":-121.1824,"mile":42.2},{"name":"Surprise Creek Trailhead","type":"trailhead","lat":47.70678,"lng":-121.15922,"mile":43.4},{"name":"Windy Point Viewpoint","type":"overlook","lat":47.71465,"lng":-121.15352,"mile":43.7},{"name":"Summit Lake","type":"lake","lat":47.73941,"lng":-121.11489,"mile":48.3,"ele":1402},{"name":"Wellington Trailhead","type":"trailhead","lat":47.74714,"lng":-121.12744,"mile":48.5},{"name":"Stevens Pass","type":"pass","lat":47.74564,"lng":-121.08917,"mile":50.1,"ele":1238},{"name":"Pacific Crest - Stevens North Trailhead","type":"trailhead","lat":47.74796,"lng":-121.08823,"mile":50.3},{"name":"Mount Weird","type":"peak","lat":47.76298,"lng":-121.06419,"mile":51.4,"ele":1531},{"name":"Bygone Byways Trailhead","type":"trailhead","lat":47.78383,"lng":-121.02907,"mile":54.7},{"name":"Lanham Lake Trailhead","type":"trailhead","lat":47.7715,"lng":-121.01446,"mile":57}],"gallery":[{"url":"https://upload.wikimedia.org/wikipedia/commons/0/0f/Mountains_to_Sound_Greenway%2C_Washington%2C_US.jpg","full":"https://upload.wikimedia.org/wikipedia/commons/0/0f/Mountains_to_Sound_Greenway%2C_Washington%2C_US.jpg","cap":", Washington, US","desc":"A map of the Mountains to Sound Greenway, an iconic landscape in Washington State. Produced by the Mountains to Sound Greenway Trust.","credit":"Mountains to Sound Greenway · CC BY-SA 3.0","pageUrl":"https://commons.wikimedia.org/wiki/File:Mountains_to_Sound_Greenway,_Washington,_US.jpg"},{"url":"https://upload.wikimedia.org/wikipedia/commons/thumb/a/a3/Mtn_to_Sound_7579.jpg/1280px-Mtn_to_Sound_7579.jpg","full":"https://upload.wikimedia.org/wikipedia/commons/a/a3/Mtn_to_Sound_7579.jpg","cap":"Mtn to Sound 7579","desc":"Mountain to Sound Trail through Judkins Park.","credit":"Chris Light · CC BY-SA 4.0","pageUrl":"https://commons.wikimedia.org/wiki/File:Mtn_to_Sound_7579.jpg"},{"url":"https://upload.wikimedia.org/wikipedia/commons/thumb/a/a3/Mtn_to_Sound_Trl_7586.jpg/1280px-Mtn_to_Sound_Trl_7586.jpg","full":"https://upload.wikimedia.org/wikipedia/commons/a/a3/Mtn_to_Sound_Trl_7586.jpg","cap":"Mtn to Sound Trl 7586","desc":"Mountain to Sound Trail through Judkins Park.","credit":"Chris Light · CC BY-SA 4.0","pageUrl":"https://commons.wikimedia.org/wiki/File:Mtn_to_Sound_Trl_7586.jpg"},{"url":"https://upload.wikimedia.org/wikipedia/commons/thumb/9/92/LW_Loop_Trl_7613.jpg/1280px-LW_Loop_Trl_7613.jpg","full":"https://upload.wikimedia.org/wikipedia/commons/9/92/LW_Loop_Trl_7613.jpg","cap":"LW Loop Trl 7613","desc":"East Portal Viewpoint on the east side of Mt. Baker overlooking Lake Washington and Mercer Island.","credit":"Chris Light · CC BY-SA 4.0","pageUrl":"https://commons.wikimedia.org/wiki/File:LW_Loop_Trl_7613.jpg"},{"url":"https://upload.wikimedia.org/wikipedia/commons/thumb/8/89/LW_Loop_Trl_7614.jpg/1280px-LW_Loop_Trl_7614.jpg","full":"https://upload.wikimedia.org/wikipedia/commons/8/89/LW_Loop_Trl_7614.jpg","cap":"LW Loop Trl 7614","desc":"East Portal Viewpoint on the east side of Mt. Baker overlooking Lake Washington and Mercer Island.","credit":"Chris Light · CC BY-SA 4.0","pageUrl":"https://commons.wikimedia.org/wiki/File:LW_Loop_Trl_7614.jpg"},{"url":"https://upload.wikimedia.org/wikipedia/commons/thumb/6/68/LW_Loop_Trl_7615.jpg/1280px-LW_Loop_Trl_7615.jpg","full":"https://upload.wikimedia.org/wikipedia/commons/6/68/LW_Loop_Trl_7615.jpg","cap":"LW Loop Trl 7615","desc":"East Portal Viewpoint on the east side of Mt. Baker overlooking Lake Washington and Mercer Island.","credit":"Chris Light · CC BY-SA 4.0","pageUrl":"https://commons.wikimedia.org/wiki/File:LW_Loop_Trl_7615.jpg"},{"url":"https://upload.wikimedia.org/wikipedia/commons/thumb/2/24/Mt_to_Sound_Trl_7609.jpg/1280px-Mt_to_Sound_Trl_7609.jpg","full":"https://upload.wikimedia.org/wikipedia/commons/2/24/Mt_to_Sound_Trl_7609.jpg","cap":"Mt to Sound Trl 7609","desc":"East Portal Viewpoint on the east side of Mt. Baker overlooking Lake Washington and Mercer Island.","credit":"Chris Light · CC BY-SA 4.0","pageUrl":"https://commons.wikimedia.org/wiki/File:Mt_to_Sound_Trl_7609.jpg"},{"url":"https://upload.wikimedia.org/wikipedia/commons/thumb/8/88/Mt_to_Sound_Trl_7610.jpg/1280px-Mt_to_Sound_Trl_7610.jpg","full":"https://upload.wikimedia.org/wikipedia/commons/8/88/Mt_to_Sound_Trl_7610.jpg","cap":"Mt to Sound Trl 7610","desc":"East Portal Viewpoint on the east side of Mt. Baker overlooking Lake Washington and Mercer Island.","credit":"Chris Light · CC BY-SA 4.0","pageUrl":"https://commons.wikimedia.org/wiki/File:Mt_to_Sound_Trl_7610.jpg"},{"url":"https://upload.wikimedia.org/wikipedia/commons/thumb/e/ed/Mt_to_Sound_Trl_7611.jpg/1280px-Mt_to_Sound_Trl_7611.jpg","full":"https://upload.wikimedia.org/wikipedia/commons/e/ed/Mt_to_Sound_Trl_7611.jpg","cap":"Mt to Sound Trl 7611","desc":"East Portal Viewpoint on the east side of Mt. Baker overlooking Lake Washington and Mercer Island.","credit":"Chris Light · CC BY-SA 4.0","pageUrl":"https://commons.wikimedia.org/wiki/File:Mt_to_Sound_Trl_7611.jpg"}]}