{"id":"peter-norbeck-scenic-byway","generatedAt":"2026-07-10T18:35:17.820Z","designation":"National Scenic Byway","parkCode":null,"source":{"roadArticle":"Peter Norbeck Scenic Byway","revisionId":1345476083,"url":"https://en.wikipedia.org/wiki/Peter_Norbeck_Scenic_Byway"},"attribution":{"license":"CC BY-SA 4.0","licenseUrl":"https://creativecommons.org/licenses/by-sa/4.0/","articleUrl":"https://en.wikipedia.org/wiki/Peter_Norbeck_Scenic_Byway","text":"Route, junction, and history details adapted from the Wikipedia article \"Peter Norbeck Scenic Byway\", by Wikipedia contributors, licensed under CC BY-SA 4.0."},"sources":[{"name":"Wikipedia","src":"wikipedia","url":"https://en.wikipedia.org/wiki/Peter_Norbeck_Scenic_Byway","revisionId":1345476083,"retrievedAt":"2026-07-10T18:35:17.820Z"},{"name":"Federal Highway Administration — National Scenic Byways","src":"fhwa","url":"https://www.fhwa.dot.gov/byways","retrievedAt":"2026-07-10T18:35:17.820Z"}],"endpoints":null,"itinerary":[],"history":{"paragraphs":["Most of the roads which make up the Peter Norbeck Scenic Byway were proposed by Peter Norbeck when he was a U.S. Senator. Norbeck's first major proposal was the Needles Highway, which comprises the SD 87 portion of the byway and cuts through the Needles. Though engineers of the time said a highway could not be built in the Needles, the highway still came into existence. Norbeck also proposed the Iron Mountain Road, the US 16A section of the byway. The byway was established on September 23, 1996, and named in honor of Norbeck."],"sourceSection":"History","src":"wikipedia"},"highlights":[],"references":[{"n":1,"text":"\"Needle's Eye in SD, a nerve racking tunnel if you have a big vehicle\".","url":"https://www.dangerousroads.org/north-america/usa/2737-needles-eye.html"},{"n":2,"text":"Peter Norbeck vs. the Diploma Boys: Building the Impossible Road","url":"http://www.byways.org/explore/byways/2459/stories/64787"}]}